.gitignore
MANIFEST.in
README.rst
setup.cfg
setup.py
docs/HISTORY.txt
docs/LICENSE.GPL
docs/LICENSE.txt
docs/MANUAL.txt
raptus/__init__.py
raptus.article.form.egg-info/PKG-INFO
raptus.article.form.egg-info/SOURCES.txt
raptus.article.form.egg-info/dependency_links.txt
raptus.article.form.egg-info/entry_points.txt
raptus.article.form.egg-info/namespace_packages.txt
raptus.article.form.egg-info/not-zip-safe
raptus.article.form.egg-info/requires.txt
raptus.article.form.egg-info/top_level.txt
raptus/article/__init__.py
raptus/article/form/__init__.py
raptus/article/form/configure.zcml
raptus/article/form/extender.py
raptus/article/form/forms.py
raptus/article/form/interfaces.py
raptus/article/form/browser/__init__.py
raptus/article/form/browser/configure.zcml
raptus/article/form/browser/forms.gif
raptus/article/form/browser/forms.pt
raptus/article/form/browser/forms.py
raptus/article/form/browser/header.pt
raptus/article/form/browser/header.py
raptus/article/form/i18n/raptus.article-de.po
raptus/article/form/i18n/raptus.article-fr.po
raptus/article/form/i18n/raptus.article.pot
raptus/article/form/profiles/default/metadata.xml
raptus/article/form/profiles/default/types.xml
raptus/article/form/profiles/default/viewlets.xml
raptus/article/form/profiles/default/types/Article.xml