Metadata-Version: 1.0
Name: raptus.article.form
Version: 2.0b6
Summary: Provides support for PloneFormGen
Home-page: https://github.com/Raptus/raptus.article.form
Author: Raptus AG
Author-email: dev@raptus.com
License: GPL
Platform: UNKNOWN
Classifier: Programming Language :: Python
Classifier: Topic :: Software Development :: Libraries :: Python Modules
